netconf_tool/__init__.py
netconf_tool/cli.py
netconf_tool/decorators.py
netconf_tool/helpers.py
netconf_tool/operations/__init__.py
netconf_tool/operations/capabilities.py
netconf_tool/operations/get_config.py
netconf_tool/operations/get_yang.py
netconf_tool/subscription/__init__.py
netconf_tool/subscription/local.py
netconf_tool/subscription/rabbitmq.py
netconf_tool/subscription/redis.py
netconf_tool/yangcli/__init__.py
netconf_tool/yangcli/get_config.py
netconf_tool-0.0.4.dist-info/METADATA
netconf_tool-0.0.4.dist-info/WHEEL
netconf_tool-0.0.4.dist-info/entry_points.txt
netconf_tool-0.0.4.dist-info/top_level.txt
netconf_tool-0.0.4.dist-info/RECORD
