Metadata-Version: 2.1
Name: netconf-tool
Version: 0.0.4
Summary: Click CLI application to help with NETCONF development experience
Home-page: https://github.com/BSpendlove/netconf-tool
Requires-Dist: ncclient (>=0.6.13)
Requires-Dist: loguru (>=0.7.0)
Requires-Dist: click (>=8.1.3)
Requires-Dist: click-plugins (>=1.1.1)
Requires-Dist: redis (>=4.5.4)
Requires-Dist: pika (>=1.3.1)
Requires-Dist: xmltodict (>=0.13.0)
